Workbook

Sheet README
A1: Vodafone Group Plc: Credit Metrics and Euro DCM Issuance Walkthrough
A3: Purpose | B3: Supports the companion credit note (Vodafone_Credit_Note, delivered as a separate .docx/.pdf) and prices an illustrative new euro 10-year off Vodafone's own bond curve.
A4: As of | B4: 16 October 2026. Financials: FY26 (year to 31 March 2026) results of 12 May 2026 and the Q1 FY27 update of 27 July 2026. Bond quotes: Boerse Stuttgart, 15-16 Oct 2026 (two quotes dated 30 Sep are flagged on Comps).
A5: Colour code | B5: Blue = hardcoded, sourced input. Black = formula. Green = link to another sheet. Yellow fill = judgement or stale-data cell worth challenging.
A6: Pricing method | B6: Anchor on Vodafone's own secondary curve (spread to Bunds, interpolated to 10 years), add a new issue concession, then cross-check against peers and a curve regression. Peer data is a check, not an input to the price.
A7: Quoting basis | B7: Euro corporates are marketed over mid-swaps, but no public source for live swap rates was available, so the build is in Bund spreads, the basis the exchange data uses. Converting needs the 10-year swap-to-Bund basis.
A8: Scope | B8: Net debt follows Vodafone's definition (half of hybrids counted as debt). Safaricom net debt comes from its FY2026 balance sheet and may include leases. FY27 free cash flow after dividends is not rolled into pro forma net debt.

Sheet Inputs
A1: Reported inputs (EUR m unless stated)
A3: Item | B3: FY25 | C3: FY26 | D3: Unit | E3: Source
A4: Revenue | B4: 37448 | C4: 40461 | D4: EUR m | E4: Vodafone FY26 preliminary results RNS, 12 May 2026 (data.fca.org.uk NSM)
A5: Service revenue | B5: 30758 | C5: 33480 | D5: EUR m | E5: Vodafone FY26 preliminary results RNS, 12 May 2026 (data.fca.org.uk NSM)
A6: Adjusted EBITDAaL | B6: 10932 | C6: 11351 | D6: EUR m | E6: Vodafone FY26 preliminary results RNS, 12 May 2026 (data.fca.org.uk NSM)
A7: Capital additions | B7: 6862 | C7: 7291 | D7: EUR m | E7: Vodafone FY26 preliminary results RNS, 12 May 2026 (data.fca.org.uk NSM)
A8: Adjusted free cash flow | B8: 2548 | C8: 2621 | D8: EUR m | E8: Vodafone FY26 preliminary results RNS, 12 May 2026 (data.fca.org.uk NSM)
A9: Free cash flow | B9: 1850 | C9: 1795 | D9: EUR m | E9: Vodafone FY26 preliminary results RNS, 12 May 2026 (data.fca.org.uk NSM)
A10: Equity dividends paid | B10: 1787 | C10: 1093 | D10: EUR m | E10: Vodafone FY26 preliminary results RNS, 12 May 2026 (data.fca.org.uk NSM)
A11: Share buybacks | B11: 1868 | C11: 2041 | D11: EUR m | E11: Vodafone FY26 preliminary results RNS, 12 May 2026 (data.fca.org.uk NSM)
A12: Net debt (company definition) | B12: 22397 | C12: 25411 | D12: EUR m | E12: Vodafone FY26 preliminary results RNS, 12 May 2026 (data.fca.org.uk NSM)
A13: Gross debt | B13: 39960 | C13: 38604 | D13: EUR m | E13: Vodafone FY26 preliminary results RNS, 12 May 2026 (data.fca.org.uk NSM)
A14: Bonds | B14: 36402 | C14: 33828 | D14: EUR m | E14: Vodafone FY26 preliminary results RNS, 12 May 2026 (data.fca.org.uk NSM)
A15: Cash and cash equivalents | B15: 11001 | C15: 8982 | D15: EUR m | E15: Vodafone FY26 preliminary results RNS, 12 May 2026 (data.fca.org.uk NSM)
... A24: Guarantees over Australia JV loan | B24: 1479 | C24: 1031 | D24: EUR m | E24: Vodafone FY26 preliminary results RNS, 12 May 2026 (data.fca.org.uk NSM)
A26: Events and guidance (single values)
A27: Item | C27: Value | D27: Unit | E27: Source
A28: VodafoneThree buyout cash cost (completed 3 Aug 2026) | C28: 4900 | D28: EUR m | E28: Vodafone RNS / advanced-television.com, 3 Aug 2026. Company: +0.4x pro forma leverage.
A29: Safaricom: cash paid by Vodacom to Kenya Govt for 15% | C29: 1360 | D29: EUR m | E29: FY26 RNS. Deal completed 30 Jun 2026 (Q1 FY27 trading update).
A30: VodafoneZiggo sale cash proceeds (expected H2 2026, not yet closed) | C30: 1000 | D30: EUR m | E30: FY26 RNS.
A31: Include VodafoneZiggo proceeds? (1=yes, 0=no) | C31: 0 | D31: flag | E31: Default 0: proceeds not yet received
A32: Safaricom net debt FY2026 (KES m) | C32: 139810 | D32: KES m | E32: stockanalysis.com, Safaricom FY2026 balance sheet: total debt 166,766 less cash 26,955; may include leases
A33: EUR/KES rate | C33: 159.66 | D33: rate | E33: Vodafone FY27 guidance FX rate, Q1 FY27 update
A34: FY27 Adj. EBITDAaL guidance ex-Safaricom: low | C34: 11900 | D34: EUR m | E34: FY26 RNS, 12 May 2026
A35: FY27 Adj. EBITDAaL guidance ex-Safaricom: high | C35: 12200 | D35: EUR m | E35: FY26 RNS, 12 May 2026
A36: Safaricom EBITDAaL, pro forma 12 months | C36: 1500 | D36: EUR m | E36: FY26 RNS (9-month FY27 impact EUR 1.1bn per Q1 update)
A37: Leverage policy: top of range | C37: 2.75 | D37: x | E37: FY26 RNS: 2.25x-2.75x, target lower half
A38: Leverage policy: bottom of range | C38: 2.25 | D38: x | E38: FY26 RNS
A39: Medium-term cost of debt ambition | C39: 0.03 | D39: % | E39: FY26 results presentation, "c.3% cost of debt"
... A46: Bond maturing: 1.5% Jul 2027 coupon | C46: 0.015 | D46: % | E46: TradingView XS1652855815

Sheet Credit_Metrics
A1: Leverage and coverage trends
A3: EUR m | B3: FY25 | C3: FY26 | D3: Pro forma A: FY26 + VodafoneThree buyout | E3: Pro forma B: FY27E mid, incl. all deals
A4: Adj. EBITDAaL | B4: =Inputs!$B$6 -> 10932 | C4: =Inputs!$C$6 -> 11351 | D4: =C4 -> 11351 | E4: =AVERAGE(Inputs!$C$34,Inputs!$C$35)+Inputs!$C$36 -> 13550
A5: Net debt | B5: =Inputs!$B$12 -> 22397 | C5: =Inputs!$C$12 -> 25411 | D5: =C5+Inputs!$C$28 -> 30311 | E5: =D5+Inputs!$C$29-Inputs!$C$30*Inputs!$C$31+Inputs!$C$32/Inputs!$C$33 -> 32546.673
A6: Net debt / Adj. EBITDAaL | B6: =B5/B4 -> 2.0487559 | C6: =C5/C4 -> 2.2386574 | D6: =D5/D4 -> 2.6703374 | E6: =E5/E4 -> 2.4019685
A7: Gross debt | B7: =Inputs!$B$13 -> 39960 | C7: =Inputs!$C$13 -> 38604
A8: Gross debt / Adj. EBITDAaL | B8: =B7/B4 -> 3.6553238 | C8: =C7/C4 -> 3.4009338
A9: Total funding obligations / EBITDAaL before leases | B9: =Inputs!$B$19/Inputs!$B$20 -> 2.1065299 | C9: =Inputs!$C$19/Inputs!$C$20 -> 2.253133
A10: Underlying net financing costs (ex buyback gains) | B10: =Inputs!$B$21+Inputs!$B$22 -> 1568 | C10: =Inputs!$C$21+Inputs!$C$22 -> 1590
A11: EBITDAaL / underlying net financing costs | B11: =B4/B10 -> 6.9719388 | C11: =C4/C10 -> 7.1389937
A12: EBITDAaL / net cash interest | B12: =B4/Inputs!$B$23 -> 9.5309503 | C12: =C4/Inputs!$C$23 -> 10.143878
A13: Adj. FCF / net debt | B13: =Inputs!$B$8/B5 -> 0.11376524 | C13: =Inputs!$C$8/C5 -> 0.10314431
A14: FCF after dividends and buybacks | B14: =Inputs!$B$9-Inputs!$B$10-Inputs!$B$11 -> -1805 | C14: =Inputs!$C$9-Inputs!$C$10-Inputs!$C$11 -> -1339
A15: Capital intensity (capex / revenue) | B15: =Inputs!$B$7/Inputs!$B$4 -> 0.18324076 | C15: =Inputs!$C$7/Inputs!$C$4 -> 0.18019822
A16: Adj. EBITDAaL margin (on revenue) | B16: =B4/Inputs!$B$4 -> 0.2919248 | C16: =C4/Inputs!$C$4 -> 0.28054176
A17: Liquidity: cash + short-term investments | B17: =Inputs!$B$15+Inputs!$B$16 -> 16281 | C17: =Inputs!$C$15+Inputs!$C$16 -> 12413
A18: Revenue | B18: =Inputs!$B$4 -> 37448 | C18: =Inputs!$C$4 -> 40461
A19: Service revenue growth | C19: =Inputs!$C$5/Inputs!$B$5-1 -> 0.088497302
A21: Pro forma B holds net debt at the post-deal level and ignores FY27 free cash flow after dividends, which would reduce net debt modestly. It annualises Safaricom EBITDAaL (9 months consolidated in FY27 guidance). Safaricom net debt (KES 139.8bn, about EUR 0.9bn) is included; the VodafoneZiggo proceeds are excluded until received (toggle on Inputs).
A24: Sensitivity: pro forma net debt / EBITDAaL (x)
A25: Rows: FY27E EBITDAaL incl. annualised Safaricom (EUR m). Columns: extra net debt on top of the base case (EUR m), e.g. deals or buybacks.
A26: EBITDAaL case | B26: 0 | C26: 1000 | D26: 2000 | E26: 3000 | F26: EBITDAaL used
A27: Low guidance | B27: =(E5+B$26)/$F27 -> 2.4288562 | C27: =(E5+C$26)/$F27 -> 2.5034831 | D27: =(E5+D$26)/$F27 -> 2.5781099 | E27: =(E5+E$26)/$F27 -> 2.6527368 | F27: =Inputs!$C$34+Inputs!$C$36 -> 13400
A28: Mid guidance | B28: =(E5+B$26)/$F28 -> 2.4019685 | C28: =(E5+C$26)/$F28 -> 2.4757692 | D28: =(E5+D$26)/$F28 -> 2.54957 | E28: =(E5+E$26)/$F28 -> 2.6233707 | F28: =E4 -> 13550
A29: High guidance | B29: =(E5+B$26)/$F29 -> 2.3756696 | C29: =(E5+C$26)/$F29 -> 2.4486623 | D29: =(E5+D$26)/$F29 -> 2.521655 | E29: =(E5+E$26)/$F29 -> 2.5946477 | F29: =Inputs!$C$35+Inputs!$C$36 -> 13700
A30: Mid less 5% (stress) | B30: =(E5+B$26)/$F30 -> 2.5283879 | C30: =(E5+C$26)/$F30 -> 2.6060729 | D30: =(E5+D$26)/$F30 -> 2.6837579 | E30: =(E5+E$26)/$F30 -> 2.7614429 | F30: =E4*0.95 -> 12872.5
A33: Headroom vs leverage policy (Pro forma B)
A34: Threshold | B34: x | C34: Net debt capacity (EUR m) | D34: Headroom (EUR m) | E34: EBITDAaL fall tolerated
A35: Policy: bottom of range | B35: =Inputs!$C$38 -> 2.25 | C35: =B35*$E$4 -> 30487.5 | D35: =C35-$E$5 -> -2059.1733 | E35: =1-$E$5/C35 -> -0.06754156
A36: Policy: top of range | B36: =Inputs!$C$37 -> 2.75 | C36: =B36*$E$4 -> 37262.5 | D36: =C36-$E$5 -> 4715.8267 | E36: =1-$E$5/C36 -> 0.12655691
A38: Negative headroom means the case sits above that threshold. Company target is the lower half of 2.25x to 2.75x (below c.2.5x).

Sheet Comps
A1: Own curve and peers: euro senior bonds, spread to Bunds
A2: Prices from Boerse Stuttgart bond pages (yield and "yield spread Bundesanleihe", maturity-matched). Quotes are bid/ask mid-market indications, not trades. Yellow = quote dated 30 Sep, so stale by two weeks.
A3: As-of date | B3: 46311
A4: Bond | B4: Maturity | C4: Years to maturity | D4: Coupon | E4: Yield | F4: Spread to Bund (bp) | G4: Quote date | H4: Source
A5: Vodafone own curve
A6: Vodafone 1.625% Nov 2030 | B6: 47811 | C6: =(B6-$B$3)/365.25 -> 4.1067762 | D6: 0.01625 | E6: 0.0405 | F6: 88.9 | G6: 46311 | H6: boerse-stuttgart.de/.../a2r2uh-vodafone-group-plc-eo-medium-term-notes-2019-30
A7: Vodafone 2.75% Dec 2034 | B7: 49279 | C7: =(B7-$B$3)/365.25 -> 8.1259411 | D7: 0.0275 | E7: 0.0455 | F7: 101 | G7: 46295 | H7: boerse-stuttgart.de/.../a1zsxb-vodafone-group-plc-eo-med--term-notes-2014-34
A8: Vodafone 2.875% Nov 2037 | B8: 50364 | C8: =(B8-$B$3)/365.25 -> 11.096509 | D8: 0.02875 | E8: 0.0471 | F8: 123.3 | G8: 46311 | H8: boerse-stuttgart.de/.../a19smk-vodafone-group-plc-eo-medium-term-notes-2017-37
A9: Vodafone 2.5% May 2039 | B9: 50914 | C9: =(B9-$B$3)/365.25 -> 12.602327 | D9: 0.025 | E9: 0.048 | F9: 117.7 | G9: 46311 | H9: boerse-stuttgart.de/.../a2r2uj-vodafone-group-plc-eo-medium-term-notes-2019-39
A11: Own-curve fair value at 10 years
A12: Bracket interpolation (Dec 2034 to Nov 2037), bp | F12: =F7+(10-C7)/(C8-C7)*(F8-F7) -> 115.06853
A13: Curve slope across own bonds (bp per year) | F13: =SLOPE(F6:F9,C6:C9) -> 3.9587698
A14: Regression fit at 10 years, 3 longest bonds (bp) | F14: =INTERCEPT(F7:F9,C7:C9)+SLOPE(F7:F9,C7:C9)*10 -> 111.40972
A15: Interpolation less regression (bp) | F15: =F12-F14 -> 3.658807
A17: Peers (cross-check only)
A18: Bond | B18: Maturity | C18: Years to maturity | D18: Coupon | E18: Yield | F18: Spread to Bund (bp) | G18: Spread adj. to 10y (bp) | H18: Source
A19: Deutsche Telekom 2.2% Jul 2033 | B19: 48785 | C19: =(B19-$B$3)/365.25 -> 6.7734428 | D19: 0.022 | E19: 0.0422 | F19: 89.5 | G19: =F19+$F$13*(10-C19) -> 102.2732 | H19: boerse-stuttgart.de/.../a193rr-deutsche-telekom-intl-fin-b-v-eo-medium-term-notes-2018-33 (15 Oct)
A20: Orange 3.25% Jan 2035 | B20: 49326 | C20: =(B20-$B$3)/365.25 -> 8.2546201 | D20: 0.0325 | E20: 0.045 | F20: 108.9 | G20: =F20+$F$13*(10-C20) -> 115.80956 | H20: boerse-stuttgart.de/.../a3l3g9-orange-35 (15 Oct)
A21: Telefonica 3.941% Jun 2035 | B21: 49485 | C21: =(B21-$B$3)/365.25 -> 8.6899384 | D21: 0.03941 | E21: 0.0482 | F21: 141.7 | G21: =F21+$F$13*(10-C21) -> 146.88623 | H21: boerse-stuttgart.de/.../a4ec6e-telefonica-emisiones-... (16 Oct)
A22: BT 3.75% Mar 2035 | B22: 49369 | C22: =(B22-$B$3)/365.25 -> 8.3723477 | D22: 0.0375 | E22: 0.0465 | F22: 104.5 | G22: =F22+$F$13*(10-C22) -> 110.9435 | H22: boerse-stuttgart.de/.../a4eb4m-british-telecommunications-... (30 Sep quote)
A24: Peer average adjusted to 10 years (bp) | G24: =AVERAGE(G19:G22) -> 118.97812
A25: Peer minimum / maximum (bp) | F25: =MIN(G19:G22) -> 102.2732 | G25: =MAX(G19:G22) -> 146.88623
A26: Vodafone own curve less peer average (bp) | G26: =F12-G24 -> -3.9095965
A28: Peers are adjusted to 10 years with Vodafone's own curve slope. No rating adjustment is applied: the price rests on Vodafone's own bonds, and the peer set (a BBB+ and a BBB- name among them) only checks that level is sensible.

Sheet DCM_Pricing
A1: Illustrative new issue: Vodafone Group Plc 10-year EUR senior unsecured benchmark
A2: Priced off Vodafone's own secondary curve; peers and a regression are cross-checks. Quoted as a spread to the 10-year Bund.
A4: Step | B4: Value | C4: Notes
A5: Pricing date | B5: 46315 | C5: Hypothetical
A6: Settlement date | B6: =B5+7 -> 46322 | C6: T+7, typical euro corporate
A7: Tenor (years) | B7: 10 | C7: Benchmark 10-year
A8: Maturity | B8: =EDATE(B6,12*B7) -> 49975
A9: Size (EUR m) | B9: 1000 | C9: Benchmark size
A10: 10-year Bund yield (15 Oct 2026) | B10: =Inputs!$C$40 -> 0.0338 | C10: Trading Economics
A11: 1. Own-curve spread at 10 years (bp) | B11: =Comps!F12 -> 115.06853 | C11: Interpolated between Vodafone Dec 2034 and Nov 2037 bonds
A12: 2. New issue concession (bp) | B12: =Inputs!$C$42 -> 0 | C12: IFR on Vodafone's last euro multi-tranche: flat to fair value, shortest tranche -5bp
A13: Re-offer spread to Bund (bp) | B13: =B11+B12 -> 115.06853
A14: Re-offer yield | B14: =B10+B13/10000 -> 0.045306853 | C14: 10-year Bund plus spread
A15: Coupon (rounded down to nearest 1/8%) | B15: =FLOOR(B14,0.00125) -> 0.045 | C15: Market convention keeps price at or just under par
A16: Issue price (per 100) | B16: =PRICE(B6,B8,B15,B14,100,1,1) -> 99.757562 | C16: Annual coupon, ICMA basis
A17: DV01 (EUR per 1bp, whole deal) | B17: =B9*1000000*(PRICE(B6,B8,B15,B14-0.0001,100,1,1)-PRICE(B6,B8,B15,B14+0.0001,100,1,1))/2/100 -> 788888.39 | C17: Price sensitivity for investors
A19: Cross-checks on the own-curve spread
A20: Check | B20: Spread (bp) | C20: Difference vs own curve (bp)
A21: Own-curve interpolation | B21: =Comps!F12 -> 115.06853 | C21: =B21-$B$21 -> 0
A22: Regression across three longest own bonds | B22: =Comps!F14 -> 111.40972 | C22: =B22-$B$21 -> -3.658807
A23: Peer average adjusted to 10 years | B23: =Comps!G24 -> 118.97812 | C23: =B23-$B$21 -> 3.9095965
A24: Peer range, low | B24: =Comps!F25 -> 102.2732 | C24: =B24-$B$21 -> -12.795328
A25: Peer range, high | B25: =Comps!G25 -> 146.88623 | C25: =B25-$B$21 -> 31.817707
A26: The own curve sits inside the peer average and well within the peer range, so no adjustment to the own-curve level is made. The Dec 2034 point is a 30 Sep quote.
A28: Refinancing drag: replacing maturing bonds at the new coupon
A29: Bond maturing | B29: Size (EUR m) | C29: Old coupon | D29: New coupon | E29: Extra annual interest (EUR m)
A30: 0.9% Nov 2026 | B30: =Inputs!$C$43 -> 750 | C30: =Inputs!$C$44 -> 0.009 | D30: =$B$15 -> 0.045 | E30: =B30*(D30-C30) -> 27
A31: 1.5% Jul 2027 | B31: =Inputs!$C$45 -> 357.31 | C31: =Inputs!$C$46 -> 0.015 | D31: =$B$15 -> 0.045 | E31: =B31*(D31-C31) -> 10.7193
A32: Total | E32: =SUM(E30:E31) -> 37.7193
A33: New coupon less c.3% cost-of-debt ambition (bp) | E33: =(B15-Inputs!$C$39)*10000 -> 150
A35: Price grid at the fixed coupon: price per 100 if the re-offer yield moves. Rows: spread change (bp). Columns: Bund move before pricing (bp).
A36: Spread change / Bund move | B36: -50 | C36: -25 | D36: 0 | E36: 25 | F36: 50
A37: -20 | B37: =PRICE($B$6,$B$8,$B$15,$B$14+($A37+B$36)/10000,100,1,1) -> 105.47479 | C37: =PRICE($B$6,$B$8,$B$15,$B$14+($A37+C$36)/10000,100,1,1) -> 103.3874 | D37: =PRICE($B$6,$B$8,$B$15,$B$14+($A37+D$36)/10000,100,1,1) -> 101.35096 | E37: =PRICE($B$6,$B$8,$B$15,$B$14+($A37+E$36)/10000,100,1,1) -> 99.364086 | F37: =PRICE($B$6,$B$8,$B$15,$B$14+($A37+F$36)/10000,100,1,1) -> 97.42541
A38: -10 | B38: =PRICE($B$6,$B$8,$B$15,$B$14+($A38+B$36)/10000,100,1,1) -> 104.63363 | C38: =PRICE($B$6,$B$8,$B$15,$B$14+($A38+C$36)/10000,100,1,1) -> 102.56679 | D38: =PRICE($B$6,$B$8,$B$15,$B$14+($A38+D$36)/10000,100,1,1) -> 100.55034 | E38: =PRICE($B$6,$B$8,$B$15,$B$14+($A38+E$36)/10000,100,1,1) -> 98.582906 | F38: =PRICE($B$6,$B$8,$B$15,$B$14+($A38+F$36)/10000,100,1,1) -> 96.66314
A39: 0 | B39: =PRICE($B$6,$B$8,$B$15,$B$14+($A39+B$36)/10000,100,1,1) -> 103.80075 | C39: =PRICE($B$6,$B$8,$B$15,$B$14+($A39+C$36)/10000,100,1,1) -> 101.75424 | D39: =PRICE($B$6,$B$8,$B$15,$B$14+($A39+D$36)/10000,100,1,1) -> 99.757562 | E39: =PRICE($B$6,$B$8,$B$15,$B$14+($A39+E$36)/10000,100,1,1) -> 97.809352 | F39: =PRICE($B$6,$B$8,$B$15,$B$14+($A39+F$36)/10000,100,1,1) -> 95.908289
A40: 10 | B40: =PRICE($B$6,$B$8,$B$15,$B$14+($A40+B$36)/10000,100,1,1) -> 102.97608 | C40: =PRICE($B$6,$B$8,$B$15,$B$14+($A40+C$36)/10000,100,1,1) -> 100.94967 | D40: =PRICE($B$6,$B$8,$B$15,$B$14+($A40+D$36)/10000,100,1,1) -> 98.972537 | E40: =PRICE($B$6,$B$8,$B$15,$B$14+($A40+E$36)/10000,100,1,1) -> 97.043342 | F40: =PRICE($B$6,$B$8,$B$15,$B$14+($A40+F$36)/10000,100,1,1) -> 95.160775
A41: 20 | B41: =PRICE($B$6,$B$8,$B$15,$B$14+($A41+B$36)/10000,100,1,1) -> 102.15951 | C41: =PRICE($B$6,$B$8,$B$15,$B$14+($A41+C$36)/10000,100,1,1) -> 100.15298 | D41: =PRICE($B$6,$B$8,$B$15,$B$14+($A41+D$36)/10000,100,1,1) -> 98.195181 | E41: =PRICE($B$6,$B$8,$B$15,$B$14+($A41+E$36)/10000,100,1,1) -> 96.284792 | F41: =PRICE($B$6,$B$8,$B$15,$B$14+($A41+F$36)/10000,100,1,1) -> 94.420519

Sheet Anchor_Deal
A1: Calibration: the real Feb 2026 15-year print against today's curve
A3: Item | B3: Value | C3: Source / note
A4: Coupon | B4: 0.04125 | C4: Cbonds new-issue notice (EUR 500m due 27 Apr 2041)
A5: Issue price (per 100) | B5: 98.515 | C5: Cbonds
A6: Reported yield at issue | B6: 0.04261 | C6: Cbonds
A7: Settlement (assumed T+7 from 24 Feb pricing) | B7: 46084 | C7: Convention
A8: Maturity | B8: 51618 | C8: Cbonds
A9: Yield recomputed from price | B9: =YIELD(B7,B8,B4,B5,100,1,1) -> 0.04259014
A10: Difference vs reported (bp) | B10: =(B9-B6)*10000 -> -0.19860075 | C10: A tie within 0.5bp confirms the price and yield mechanics used in DCM_Pricing
A12: Feb 2026 print over the 10-year Bund (bp) | B12: =(B6-Inputs!$C$41)*10000 -> 156.1 | C12: Bund 10y 2.70% on 26 Feb 2026
A13: Today: Vodafone 2.5% May 2039 over the 10-year Bund (bp) | B13: =(Comps!E9-Inputs!$C$40)*10000 -> 142 | C13: Closest own bond to a 15-year; 12.6 years left
A14: Bund 10y move since Feb (bp) | B14: =(Inputs!$C$40-Inputs!$C$41)*10000 -> 68
A15: Actual change in Vodafone long-end yield (bp) | B15: =(Comps!E9-B6)*10000 -> 53.9 | C15: 2039 bond today vs 2041 print
A16: Maturity roll-down on own curve (bp) | B16: =-Comps!F13*((B8-B7)/365.25-Comps!C9) -> -10.090663 | C16: Own-curve slope x 2.5 years shorter
A17: Expected change: Bund move plus roll-down (bp) | B17: =B14+B16 -> 57.909337
A18: Residual: spread change not explained (bp) | B18: =B15-B17 -> -4.0093369 | C18: Small residual: the own curve today is consistent with the real Feb print once the Bund move is allowed for
A20: Modelled new 10-year yield (DCM_Pricing) | B20: =DCM_Pricing!B14 -> 0.045306853
A21: Less Feb 2026 15-year yield (bp) | B21: =(B20-B6)*10000 -> 26.968525 | C21: Higher mainly because Bunds are up; the shorter tenor offsets part of it

Sheet Terms_Covenants
A1: Market conventions: investment-grade vs high-yield euro senior notes
A2: General market convention, shown to frame how an IG issuer such as Vodafone differs from a HY issuer. Vodafone-specific facts are sourced in the notes column.
A4: Term | B4: Investment grade | C4: High yield | D4: Vodafone fact and source
A5: Issuer / ranking | B5: Parent-level senior unsecured | C5: Often holdco or opco with guarantees; secured or unsecured | D5: Vodafone Group Plc and Vodafone International Financing DAC issue under one EMTN programme (vodafone.com bonds outstanding)
A6: Programme size | B6: EMTN programme | C6: Standalone indenture | D6: EUR 30bn EMTN programme (vodafone.com bonds outstanding)
A7: Coupon basis | B7: Fixed, annual, ICMA Act/Act | C7: Fixed or FRN, semi-annual common | D7: Annual coupons on the EUR bonds in Comps
A8: Call features | B8: Make-whole call, short par call before maturity, tax call | C8: Non-call period then stepped call prices | D8: Not reviewed for Vodafone
A9: Financial covenants | B9: None maintained | C9: Incurrence tests: fixed charge cover, leverage, restricted payments | D9: Discipline is by policy: net debt / EBITDAaL 2.25x to 2.75x, lower half targeted (FY26 results)
A10: Negative covenants | B10: Limited protections | C10: Extensive package: debt, liens, asset sales, dividends | D10: Not reviewed for Vodafone
A11: Events of default | B11: Non-payment, breach, cross-default, insolvency | C11: Same plus covenant breach | D11: Not reviewed for Vodafone
A12: Pricing basis | B12: Spread over mid-swaps (EUR), Gilts (GBP), Treasuries (USD) | C12: Yield or spread to benchmark | D12: Vodafone marketed its last euro multi-tranche over mid-swaps (IFR)
